chronoamperometry/__init__.py
chronoamperometry/plotting.py
chronoamperometry/statistics.py
chronoamperometry/utils.py
chronoamperometry-0.1.0a4.dist-info/DESCRIPTION.rst
chronoamperometry-0.1.0a4.dist-info/METADATA
chronoamperometry-0.1.0a4.dist-info/RECORD
chronoamperometry-0.1.0a4.dist-info/WHEEL
chronoamperometry-0.1.0a4.dist-info/metadata.json
chronoamperometry-0.1.0a4.dist-info/top_level.txt
