Metadata-Version: 2.0
Name: chronoamperometry
Version: 0.1.0a4
Summary: A toolset for analyzing chronoamperometric data
Home-page: https://github.com/Zer0Credibility/chronoamperometry
Author: Clayton Rabideau
Author-email: cmr57@cam.ac.uk
License: 4-clause BSD
Platform: UNKNOWN
Requires-Dist: numpy
Requires-Dist: pandas
Requires-Dist: plotnine
Requires-Dist: tqdm
Requires-Dist: scipy
Requires-Dist: statsmodels
Requires-Dist: xlrd
